asciiasm/__about__.py
asciiasm/__init__.py
asciiasm/main.py
asciiasm/control/__init__.py
asciiasm/control/ui.py
asciiasm/editor/__init__.py
asciiasm/editor/canvas.py
asciiasm/editor/sprites.py
asciiasm/files/__init__.py
asciiasm/files/load.py
asciiasm/files/save.py
asciiasm-0.1.0.dist-info/METADATA
asciiasm-0.1.0.dist-info/WHEEL
asciiasm-0.1.0.dist-info/entry_points.txt
asciiasm-0.1.0.dist-info/licenses/LICENSE
asciiasm-0.1.0.dist-info/RECORD
