Metadata-Version: 2.4
Name: asciiasm
Version: 0.1.0
Summary: Edit ascii art scenes and control object overlay.
Project-URL: github, https://github.com/aal337/ascii-scenery-assembler
Author-email: Abdurahman Algheb <abdurahmanalgheb@gmail.com>
Maintainer-email: Abdurahman Algheb <abdurahmanalgheb@gmail.com>
License-Expression: GPL-3.0-or-later
License-File: LICENSE
Classifier: Development Status :: 5 - Production/Stable
Classifier: Environment :: Console :: Curses
Classifier: License :: OSI Approved :: GNU General Public License v3 or later (GPLv3+)
Classifier: Programming Language :: Python :: 3.12
Requires-Dist: numpy
Requires-Dist: uni-curses
